chartisan/__init__.py
chartisan/chartisan.py
chartisan/data.py
chartisan-1.2.0.dist-info/LICENSE
chartisan-1.2.0.dist-info/WHEEL
chartisan-1.2.0.dist-info/METADATA
chartisan-1.2.0.dist-info/RECORD
