Metadata-Version: 2.1
Name: chartisan
Version: 1.2.0
Summary: Chartisan's Python backend
Author: Erik Campobadal
Author-email: soc@erik.cat
Requires-Python: >=3.7,<4.0
Classifier: Programming Language :: Python :: 3
Classifier: Programming Language :: Python :: 3.7
Classifier: Programming Language :: Python :: 3.8
